{"nodes": [{"id": "c_users_rishi_desktop_foxmix_formix_backend_models_py", "label": "models.py", "file_type": "code", "source_file": "backend/models.py", "source_location": "L1"}, {"id": "c_users_rishi_desktop_foxmix_formix_backend_models_now", "label": "_now()", "file_type": "code", "source_file": "backend/models.py", "source_location": "L21", "_callable": true}, {"id": "datetime", "label": "datetime", "file_type": "code", "source_file": "", "source_location": "", "origin_file": "C:\\Users\\Rishi\\Desktop\\Foxmix\\formix\\backend\\models.py"}, {"id": "c_users_rishi_desktop_foxmix_formix_backend_models_uuid", "label": "_uuid()", "file_type": "code", "source_file": "backend/models.py", "source_location": "L25", "_callable": true}, {"id": "c_users_rishi_desktop_foxmix_formix_backend_models_user", "label": "User", "file_type": "code", "source_file": "backend/models.py", "source_location": "L31", "_callable": true}, {"id": "base", "label": "Base", "file_type": "code", "source_file": "", "source_location": "", "origin_file": "C:\\Users\\Rishi\\Desktop\\Foxmix\\formix\\backend\\models.py"}, {"id": "c_users_rishi_desktop_foxmix_formix_backend_models_project", "label": "Project", "file_type": "code", "source_file": "backend/models.py", "source_location": "L49", "_callable": true}, {"id": "c_users_rishi_desktop_foxmix_formix_backend_models_form", "label": "Form", "file_type": "code", "source_file": "backend/models.py", "source_location": "L69", "_callable": true}, {"id": "c_users_rishi_desktop_foxmix_formix_backend_models_submission", "label": "Submission", "file_type": "code", "source_file": "backend/models.py", "source_location": "L103", "_callable": true}, {"id": "c_users_rishi_desktop_foxmix_formix_backend_models_rationale_1", "label": "backend/models.py SQLAlchemy ORM models for Formix.  Tables:   - users       : a", "file_type": "rationale", "source_file": "backend/models.py", "source_location": "L1"}, {"id": "c_users_rishi_desktop_foxmix_formix_backend_models_rationale_32", "label": "An author account.  Respondents fill forms anonymously and never have an account", "file_type": "rationale", "source_file": "backend/models.py", "source_location": "L32"}, {"id": "c_users_rishi_desktop_foxmix_formix_backend_models_rationale_50", "label": "A named container that groups related forms together (like an Overleaf project).", "file_type": "rationale", "source_file": "backend/models.py", "source_location": "L50"}, {"id": "c_users_rishi_desktop_foxmix_formix_backend_models_rationale_70", "label": "A form definition created by an author.      - project_id    : which project thi", "file_type": "rationale", "source_file": "backend/models.py", "source_location": "L70"}, {"id": "c_users_rishi_desktop_foxmix_formix_backend_models_rationale_104", "label": "A single respondent's answer payload for a published form.      - respondent_ses", "file_type": "rationale", "source_file": "backend/models.py", "source_location": "L104"}], "edges": [{"source": "c_users_rishi_desktop_foxmix_formix_backend_models_py", "target": "uuid", "relation": "imports", "context": "import", "confidence": "EXTRACTED", "source_file": "backend/models.py", "source_location": "L12", "weight": 1.0}, {"source": "c_users_rishi_desktop_foxmix_formix_backend_models_py", "target": "datetime", "relation": "imports_from", "context": "import", "confidence": "EXTRACTED", "source_file": "backend/models.py", "source_location": "L13", "weight": 1.0}, {"source": "c_users_rishi_desktop_foxmix_formix_backend_models_py", "target": "sqlalchemy", "relation": "imports_from", "context": "import", "confidence": "EXTRACTED", "source_file": "backend/models.py", "source_location": "L14", "weight": 1.0}, {"source": "c_users_rishi_desktop_foxmix_formix_backend_models_py", "target": "sqlalchemy_types", "relation": "imports_from", "context": "import", "confidence": "EXTRACTED", "source_file": "backend/models.py", "source_location": "L15", "weight": 1.0}, {"source": "c_users_rishi_desktop_foxmix_formix_backend_models_py", "target": "sqlalchemy_orm", "relation": "imports_from", "context": "import", "confidence": "EXTRACTED", "source_file": "backend/models.py", "source_location": "L16", "weight": 1.0}, {"source": "c_users_rishi_desktop_foxmix_formix_backend_models_py", "target": "c_users_rishi_desktop_foxmix_formix_backend_database_py", "relation": "imports_from", "context": "import", "confidence": "EXTRACTED", "source_file": "backend/models.py", "source_location": "L18", "weight": 1.0}, {"source": "c_users_rishi_desktop_foxmix_formix_backend_models_py", "target": "c_users_rishi_desktop_foxmix_formix_backend_models_now", "relation": "contains", "confidence": "EXTRACTED", "source_file": "backend/models.py", "source_location": "L21", "weight": 1.0}, {"source": "c_users_rishi_desktop_foxmix_formix_backend_models_now", "target": "datetime", "relation": "references", "context": "return_type", "confidence": "EXTRACTED", "source_file": "backend/models.py", "source_location": "L21", "weight": 1.0}, {"source": "c_users_rishi_desktop_foxmix_formix_backend_models_py", "target": "c_users_rishi_desktop_foxmix_formix_backend_models_uuid", "relation": "contains", "confidence": "EXTRACTED", "source_file": "backend/models.py", "source_location": "L25", "weight": 1.0}, {"source": "c_users_rishi_desktop_foxmix_formix_backend_models_py", "target": "c_users_rishi_desktop_foxmix_formix_backend_models_user", "relation": "contains", "confidence": "EXTRACTED", "source_file": "backend/models.py", "source_location": "L31", "weight": 1.0}, {"source": "c_users_rishi_desktop_foxmix_formix_backend_models_user", "target": "base", "relation": "inherits", "confidence": "EXTRACTED", "source_file": "backend/models.py", "source_location": "L31", "weight": 1.0}, {"source": "c_users_rishi_desktop_foxmix_formix_backend_models_py", "target": "c_users_rishi_desktop_foxmix_formix_backend_models_project", "relation": "contains", "confidence": "EXTRACTED", "source_file": "backend/models.py", "source_location": "L49", "weight": 1.0}, {"source": "c_users_rishi_desktop_foxmix_formix_backend_models_project", "target": "base", "relation": "inherits", "confidence": "EXTRACTED", "source_file": "backend/models.py", "source_location": "L49", "weight": 1.0}, {"source": "c_users_rishi_desktop_foxmix_formix_backend_models_py", "target": "c_users_rishi_desktop_foxmix_formix_backend_models_form", "relation": "contains", "confidence": "EXTRACTED", "source_file": "backend/models.py", "source_location": "L69", "weight": 1.0}, {"source": "c_users_rishi_desktop_foxmix_formix_backend_models_form", "target": "base", "relation": "inherits", "confidence": "EXTRACTED", "source_file": "backend/models.py", "source_location": "L69", "weight": 1.0}, {"source": "c_users_rishi_desktop_foxmix_formix_backend_models_py", "target": "c_users_rishi_desktop_foxmix_formix_backend_models_submission", "relation": "contains", "confidence": "EXTRACTED", "source_file": "backend/models.py", "source_location": "L103", "weight": 1.0}, {"source": "c_users_rishi_desktop_foxmix_formix_backend_models_submission", "target": "base", "relation": "inherits", "confidence": "EXTRACTED", "source_file": "backend/models.py", "source_location": "L103", "weight": 1.0}, {"source": "c_users_rishi_desktop_foxmix_formix_backend_models_rationale_1", "target": "c_users_rishi_desktop_foxmix_formix_backend_models_py", "relation": "rationale_for", "confidence": "EXTRACTED", "source_file": "backend/models.py", "source_location": "L1", "weight": 1.0}, {"source": "c_users_rishi_desktop_foxmix_formix_backend_models_rationale_32", "target": "c_users_rishi_desktop_foxmix_formix_backend_models_user", "relation": "rationale_for", "confidence": "EXTRACTED", "source_file": "backend/models.py", "source_location": "L32", "weight": 1.0}, {"source": "c_users_rishi_desktop_foxmix_formix_backend_models_rationale_50", "target": "c_users_rishi_desktop_foxmix_formix_backend_models_project", "relation": "rationale_for", "confidence": "EXTRACTED", "source_file": "backend/models.py", "source_location": "L50", "weight": 1.0}, {"source": "c_users_rishi_desktop_foxmix_formix_backend_models_rationale_70", "target": "c_users_rishi_desktop_foxmix_formix_backend_models_form", "relation": "rationale_for", "confidence": "EXTRACTED", "source_file": "backend/models.py", "source_location": "L70", "weight": 1.0}, {"source": "c_users_rishi_desktop_foxmix_formix_backend_models_rationale_104", "target": "c_users_rishi_desktop_foxmix_formix_backend_models_submission", "relation": "rationale_for", "confidence": "EXTRACTED", "source_file": "backend/models.py", "source_location": "L104", "weight": 1.0}], "raw_calls": [{"caller_nid": "c_users_rishi_desktop_foxmix_formix_backend_models_now", "callee": "now", "is_member_call": true, "source_file": "backend/models.py", "source_location": "L22", "receiver": "datetime"}, {"caller_nid": "c_users_rishi_desktop_foxmix_formix_backend_models_uuid", "callee": "uuid4", "is_member_call": true, "source_file": "backend/models.py", "source_location": "L26", "receiver": "uuid"}]}